{
  "tier": "winter",
  "season": "Winter Stillness",
  "levels": [
    {
      "id": "win-1",
      "tier": "winter",
      "index": 0,
      "name": "Winter Stillness \u2014 1",
      "bowls": [
        [
          "celadon",
          "sakura",
          "sakura",
          "sakura",
          "cobalt"
        ],
        [
          "cobalt",
          "rust",
          "rust",
          "rust",
          "rice"
        ],
        [
          "rust",
          "celadon",
          "cobalt",
          "celadon",
          "celadon"
        ],
        [],
        [
          "tenmoku",
          "rice",
          "cobalt",
          "rice"
        ],
        [
          "sakura",
          "sakura",
          "celadon"
        ],
        [],
        [],
        [
          "tenmoku",
          "tenmoku",
          "tenmoku",
          "tenmoku",
          "cobalt"
        ],
        [],
        [
          "rice",
          "rust",
          "rice"
        ]
      ],
      "capacity": 5,
      "goldDrops": 1,
      "targetMoves": 18,
      "optimalMoves": 17,
      "palette": [
        {
          "id": "celadon",
          "name": "Celadon Jade",
          "hex": "#7fb069"
        },
        {
          "id": "cobalt",
          "name": "Cobalt Indigo",
          "hex": "#3b5ba6"
        },
        {
          "id": "rust",
          "name": "Iron Rust",
          "hex": "#b85c38"
        },
        {
          "id": "rice",
          "name": "Creamy Rice",
          "hex": "#e8dcc5"
        },
        {
          "id": "tenmoku",
          "name": "Tenmoku Black",
          "hex": "#2d2a26"
        },
        {
          "id": "sakura",
          "name": "Sakura Pink",
          "hex": "#d68c9f"
        }
      ]
    },
    {
      "id": "win-2",
      "tier": "winter",
      "index": 1,
      "name": "Winter Stillness \u2014 2",
      "bowls": [
        [
          "celadon",
          "celadon",
          "rice",
          "sakura"
        ],
        [
          "cobalt",
          "cobalt",
          "sakura"
        ],
        [
          "rust",
          "rust",
          "rust",
          "celadon",
          "rice"
        ],
        [
          "rice",
          "sakura"
        ],
        [
          "tenmoku",
          "tenmoku",
          "tenmoku",
          "tenmoku",
          "cobalt"
        ],
        [
          "sakura"
        ],
        [
          "sakura",
          "cobalt",
          "rice",
          "rice",
          "cobalt"
        ],
        [],
        [],
        [],
        [
          "rust",
          "rust",
          "celadon",
          "tenmoku",
          "celadon"
        ]
      ],
      "capacity": 5,
      "goldDrops": 1,
      "targetMoves": 18,
      "optimalMoves": 17,
      "palette": [
        {
          "id": "celadon",
          "name": "Celadon Jade",
          "hex": "#7fb069"
        },
        {
          "id": "cobalt",
          "name": "Cobalt Indigo",
          "hex": "#3b5ba6"
        },
        {
          "id": "rust",
          "name": "Iron Rust",
          "hex": "#b85c38"
        },
        {
          "id": "rice",
          "name": "Creamy Rice",
          "hex": "#e8dcc5"
        },
        {
          "id": "tenmoku",
          "name": "Tenmoku Black",
          "hex": "#2d2a26"
        },
        {
          "id": "sakura",
          "name": "Sakura Pink",
          "hex": "#d68c9f"
        }
      ]
    },
    {
      "id": "win-3",
      "tier": "winter",
      "index": 2,
      "name": "Winter Stillness \u2014 3",
      "bowls": [
        [
          "celadon",
          "celadon",
          "celadon",
          "celadon",
          "sakura"
        ],
        [],
        [],
        [
          "rice",
          "rice",
          "cobalt",
          "rust"
        ],
        [
          "tenmoku",
          "rust",
          "rust"
        ],
        [
          "sakura",
          "sakura",
          "cobalt",
          "rice",
          "rice"
        ],
        [],
        [
          "cobalt",
          "tenmoku",
          "rust"
        ],
        [],
        [
          "sakura",
          "tenmoku",
          "tenmoku",
          "rust",
          "tenmoku"
        ],
        [
          "celadon",
          "sakura",
          "rice",
          "cobalt",
          "cobalt"
        ]
      ],
      "capacity": 5,
      "goldDrops": 1,
      "targetMoves": 18,
      "optimalMoves": 17,
      "palette": [
        {
          "id": "celadon",
          "name": "Celadon Jade",
          "hex": "#7fb069"
        },
        {
          "id": "cobalt",
          "name": "Cobalt Indigo",
          "hex": "#3b5ba6"
        },
        {
          "id": "rust",
          "name": "Iron Rust",
          "hex": "#b85c38"
        },
        {
          "id": "rice",
          "name": "Creamy Rice",
          "hex": "#e8dcc5"
        },
        {
          "id": "tenmoku",
          "name": "Tenmoku Black",
          "hex": "#2d2a26"
        },
        {
          "id": "sakura",
          "name": "Sakura Pink",
          "hex": "#d68c9f"
        }
      ]
    },
    {
      "id": "win-4",
      "tier": "winter",
      "index": 3,
      "name": "Winter Stillness \u2014 4",
      "bowls": [
        [
          "celadon",
          "celadon",
          "tenmoku",
          "cobalt"
        ],
        [],
        [
          "rust",
          "rust",
          "rice",
          "cobalt"
        ],
        [
          "rice",
          "rice",
          "cobalt",
          "tenmoku"
        ],
        [
          "tenmoku",
          "tenmoku",
          "rice",
          "sakura"
        ],
        [
          "sakura",
          "sakura",
          "sakura",
          "sakura",
          "tenmoku"
        ],
        [
          "rust",
          "rust",
          "rust",
          "celadon",
          "cobalt"
        ],
        [],
        [],
        [],
        [
          "celadon",
          "celadon",
          "rice",
          "cobalt"
        ]
      ],
      "capacity": 5,
      "goldDrops": 1,
      "targetMoves": 16,
      "optimalMoves": 15,
      "palette": [
        {
          "id": "celadon",
          "name": "Celadon Jade",
          "hex": "#7fb069"
        },
        {
          "id": "cobalt",
          "name": "Cobalt Indigo",
          "hex": "#3b5ba6"
        },
        {
          "id": "rust",
          "name": "Iron Rust",
          "hex": "#b85c38"
        },
        {
          "id": "rice",
          "name": "Creamy Rice",
          "hex": "#e8dcc5"
        },
        {
          "id": "tenmoku",
          "name": "Tenmoku Black",
          "hex": "#2d2a26"
        },
        {
          "id": "sakura",
          "name": "Sakura Pink",
          "hex": "#d68c9f"
        }
      ]
    },
    {
      "id": "win-5",
      "tier": "winter",
      "index": 4,
      "name": "Winter Stillness \u2014 5",
      "bowls": [
        [
          "celadon",
          "celadon",
          "tenmoku",
          "rust"
        ],
        [
          "cobalt",
          "cobalt",
          "cobalt",
          "celadon",
          "tenmoku"
        ],
        [
          "cobalt",
          "cobalt",
          "sakura",
          "rice"
        ],
        [
          "rice",
          "rice",
          "rice",
          "celadon",
          "tenmoku"
        ],
        [
          "tenmoku",
          "tenmoku",
          "celadon",
          "rust"
        ],
        [
          "sakura",
          "sakura",
          "sakura",
          "sakura",
          "rust"
        ],
        [],
        [],
        [
          "rust",
          "rust",
          "rice"
        ],
        [],
        []
      ],
      "capacity": 5,
      "goldDrops": 1,
      "targetMoves": 16,
      "optimalMoves": 15,
      "palette": [
        {
          "id": "celadon",
          "name": "Celadon Jade",
          "hex": "#7fb069"
        },
        {
          "id": "cobalt",
          "name": "Cobalt Indigo",
          "hex": "#3b5ba6"
        },
        {
          "id": "rust",
          "name": "Iron Rust",
          "hex": "#b85c38"
        },
        {
          "id": "rice",
          "name": "Creamy Rice",
          "hex": "#e8dcc5"
        },
        {
          "id": "tenmoku",
          "name": "Tenmoku Black",
          "hex": "#2d2a26"
        },
        {
          "id": "sakura",
          "name": "Sakura Pink",
          "hex": "#d68c9f"
        }
      ]
    },
    {
      "id": "win-6",
      "tier": "winter",
      "index": 5,
      "name": "Winter Stillness \u2014 6",
      "bowls": [
        [],
        [
          "cobalt",
          "cobalt",
          "cobalt",
          "cobalt",
          "rice"
        ],
        [
          "rust",
          "rust",
          "rice",
          "celadon"
        ],
        [
          "tenmoku",
          "tenmoku",
          "tenmoku",
          "tenmoku",
          "rust"
        ],
        [
          "tenmoku",
          "rust",
          "rust",
          "celadon",
          "cobalt"
        ],
        [
          "sakura",
          "sakura",
          "rice",
          "celadon"
        ],
        [
          "rice",
          "rice",
          "celadon"
        ],
        [],
        [],
        [
          "sakura",
          "sakura",
          "sakura",
          "celadon"
        ],
        []
      ],
      "capacity": 5,
      "goldDrops": 1,
      "targetMoves": 15,
      "optimalMoves": 14,
      "palette": [
        {
          "id": "celadon",
          "name": "Celadon Jade",
          "hex": "#7fb069"
        },
        {
          "id": "cobalt",
          "name": "Cobalt Indigo",
          "hex": "#3b5ba6"
        },
        {
          "id": "rust",
          "name": "Iron Rust",
          "hex": "#b85c38"
        },
        {
          "id": "rice",
          "name": "Creamy Rice",
          "hex": "#e8dcc5"
        },
        {
          "id": "tenmoku",
          "name": "Tenmoku Black",
          "hex": "#2d2a26"
        },
        {
          "id": "sakura",
          "name": "Sakura Pink",
          "hex": "#d68c9f"
        }
      ]
    },
    {
      "id": "win-7",
      "tier": "winter",
      "index": 6,
      "name": "Winter Stillness \u2014 7",
      "bowls": [
        [
          "celadon",
          "sakura",
          "sakura",
          "sakura",
          "tenmoku"
        ],
        [
          "cobalt",
          "cobalt",
          "rice",
          "celadon",
          "rice"
        ],
        [],
        [
          "rice",
          "rice",
          "rust",
          "cobalt",
          "sakura"
        ],
        [
          "tenmoku",
          "tenmoku",
          "tenmoku",
          "tenmoku",
          "rust"
        ],
        [
          "sakura",
          "cobalt",
          "cobalt",
          "rice",
          "rust"
        ],
        [],
        [
          "celadon",
          "rust"
        ],
        [
          "celadon",
          "celadon",
          "rust"
        ],
        [],
        []
      ],
      "capacity": 5,
      "goldDrops": 1,
      "targetMoves": 17,
      "optimalMoves": 16,
      "palette": [
        {
          "id": "celadon",
          "name": "Celadon Jade",
          "hex": "#7fb069"
        },
        {
          "id": "cobalt",
          "name": "Cobalt Indigo",
          "hex": "#3b5ba6"
        },
        {
          "id": "rust",
          "name": "Iron Rust",
          "hex": "#b85c38"
        },
        {
          "id": "rice",
          "name": "Creamy Rice",
          "hex": "#e8dcc5"
        },
        {
          "id": "tenmoku",
          "name": "Tenmoku Black",
          "hex": "#2d2a26"
        },
        {
          "id": "sakura",
          "name": "Sakura Pink",
          "hex": "#d68c9f"
        }
      ]
    },
    {
      "id": "win-8",
      "tier": "winter",
      "index": 7,
      "name": "Winter Stillness \u2014 8",
      "bowls": [
        [
          "celadon",
          "celadon",
          "sakura"
        ],
        [],
        [
          "rust",
          "rust",
          "rust",
          "rust",
          "rice"
        ],
        [
          "rice",
          "rice",
          "rice",
          "rice",
          "tenmoku"
        ],
        [
          "tenmoku",
          "tenmoku",
          "tenmoku",
          "tenmoku",
          "cobalt"
        ],
        [
          "sakura",
          "sakura",
          "celadon"
        ],
        [
          "cobalt",
          "cobalt",
          "cobalt",
          "sakura",
          "celadon"
        ],
        [],
        [],
        [],
        [
          "sakura",
          "rust",
          "cobalt",
          "celadon"
        ]
      ],
      "capacity": 5,
      "goldDrops": 1,
      "targetMoves": 14,
      "optimalMoves": 13,
      "palette": [
        {
          "id": "celadon",
          "name": "Celadon Jade",
          "hex": "#7fb069"
        },
        {
          "id": "cobalt",
          "name": "Cobalt Indigo",
          "hex": "#3b5ba6"
        },
        {
          "id": "rust",
          "name": "Iron Rust",
          "hex": "#b85c38"
        },
        {
          "id": "rice",
          "name": "Creamy Rice",
          "hex": "#e8dcc5"
        },
        {
          "id": "tenmoku",
          "name": "Tenmoku Black",
          "hex": "#2d2a26"
        },
        {
          "id": "sakura",
          "name": "Sakura Pink",
          "hex": "#d68c9f"
        }
      ]
    },
    {
      "id": "win-9",
      "tier": "winter",
      "index": 8,
      "name": "Winter Stillness \u2014 9",
      "bowls": [
        [],
        [
          "cobalt",
          "rust",
          "rust",
          "celadon",
          "rust"
        ],
        [
          "rust",
          "celadon",
          "celadon"
        ],
        [
          "rice",
          "rice",
          "cobalt",
          "rust",
          "celadon"
        ],
        [
          "tenmoku",
          "tenmoku",
          "cobalt",
          "sakura",
          "celadon"
        ],
        [
          "sakura",
          "sakura",
          "sakura",
          "sakura",
          "cobalt"
        ],
        [
          "tenmoku",
          "cobalt",
          "tenmoku"
        ],
        [
          "rice",
          "rice",
          "rice",
          "tenmoku"
        ],
        [],
        [],
        []
      ],
      "capacity": 5,
      "goldDrops": 1,
      "targetMoves": 18,
      "optimalMoves": 17,
      "palette": [
        {
          "id": "celadon",
          "name": "Celadon Jade",
          "hex": "#7fb069"
        },
        {
          "id": "cobalt",
          "name": "Cobalt Indigo",
          "hex": "#3b5ba6"
        },
        {
          "id": "rust",
          "name": "Iron Rust",
          "hex": "#b85c38"
        },
        {
          "id": "rice",
          "name": "Creamy Rice",
          "hex": "#e8dcc5"
        },
        {
          "id": "tenmoku",
          "name": "Tenmoku Black",
          "hex": "#2d2a26"
        },
        {
          "id": "sakura",
          "name": "Sakura Pink",
          "hex": "#d68c9f"
        }
      ]
    },
    {
      "id": "win-10",
      "tier": "winter",
      "index": 9,
      "name": "Winter Stillness \u2014 10",
      "bowls": [
        [
          "celadon",
          "celadon",
          "rice",
          "rice",
          "rust"
        ],
        [
          "cobalt",
          "sakura",
          "sakura",
          "sakura",
          "rust"
        ],
        [
          "rust",
          "rust",
          "celadon"
        ],
        [
          "rice",
          "sakura",
          "cobalt"
        ],
        [
          "tenmoku",
          "tenmoku",
          "celadon"
        ],
        [
          "sakura",
          "cobalt",
          "cobalt",
          "rice"
        ],
        [],
        [
          "rust",
          "cobalt",
          "celadon"
        ],
        [
          "tenmoku",
          "tenmoku",
          "tenmoku",
          "rice"
        ],
        [],
        []
      ],
      "capacity": 5,
      "goldDrops": 1,
      "targetMoves": 17,
      "optimalMoves": 16,
      "palette": [
        {
          "id": "celadon",
          "name": "Celadon Jade",
          "hex": "#7fb069"
        },
        {
          "id": "cobalt",
          "name": "Cobalt Indigo",
          "hex": "#3b5ba6"
        },
        {
          "id": "rust",
          "name": "Iron Rust",
          "hex": "#b85c38"
        },
        {
          "id": "rice",
          "name": "Creamy Rice",
          "hex": "#e8dcc5"
        },
        {
          "id": "tenmoku",
          "name": "Tenmoku Black",
          "hex": "#2d2a26"
        },
        {
          "id": "sakura",
          "name": "Sakura Pink",
          "hex": "#d68c9f"
        }
      ]
    }
  ]
}